.gitignore
LICENSE
README.md
example.json
setup.cfg
setup.py
./ToolBoxAssistant/bin/tba
ToolBoxAssistant/__init__.py
ToolBoxAssistant/app.py
ToolBoxAssistant/helpers.py
ToolBoxAssistant/log.py
ToolBoxAssistant.egg-info/PKG-INFO
ToolBoxAssistant.egg-info/SOURCES.txt
ToolBoxAssistant.egg-info/dependency_links.txt
ToolBoxAssistant.egg-info/top_level.txt
ToolBoxAssistant.egg-info/zip-safe
ToolBoxAssistant/bin/tba