Metadata-Version: 1.1
Name: ToolBoxAssistant
Version: 0.1
Summary: An utility to easily manage your toolbox applications
Home-page: https://github.com/mattoufoutu/ToolBoxAssistant
Author: Mathieu D. (MatToufoutu)
Author-email: mattoufootu+code@gmail.com
License: GPL
Keywords: toolbox tools applications management utility
Platform: UNKNOWN
Classifier: Development Status :: 4 - Beta
Classifier: Environment :: Console
Classifier: License :: OSI Approved :: GNU General Public License v3 (GPLv3)
Classifier: Natural Language :: English
Classifier: Operating System :: OS Independent
Classifier: Programming Language :: Python :: 2.7
Classifier: Topic :: Utilities
